buckets/__init__.py
buckets/__main__.py
buckets/fake/__init__.py
buckets/fake/cases_rows.py
buckets/fake/console.py
buckets/fake/dates.py
buckets/fake/users.py
buckets/services/__init__.py
buckets/services/cases_buckets.py
buckets/services/config_service.py
schema_analyzer/__init__.py
schema_analyzer/classes/__init__.py
schema_analyzer/scripts/__init__.py
schema_analyzer/scripts/main.py
schema_analyzer/services/__init__.py
schema_analyzer/services/files.py
speedy/__init__.py
speedy/__main__.py
speedy/fake/__init__.py
speedy/fake/dates.py
speedy/fake/security_log_rows.py
speedy/fake/users.py
speedy/services/__init__.py
speedy/services/config_service.py
speedy/services/database_service.py
speedy/services/security_logs_service.py
statspm4/__init__.py
statspm4/app.py
statspm4/main.py
statspm4/classes/__init__.py
statspm4/classes/pm4_stats.py
statspm4/classes/zip_file.py
statspm4/scripts/__init__.py
statspm4/services/__init__.py
statspm4/services/config_service.py
statspm4/services/files.py
PyArchitect-1.0.29.dist-info/METADATA
PyArchitect-1.0.29.dist-info/WHEEL
PyArchitect-1.0.29.dist-info/entry_points.txt
PyArchitect-1.0.29.dist-info/top_level.txt
PyArchitect-1.0.29.dist-info/RECORD
