Metadata-Version: 2.1
Name: PyArchitect
Version: 1.0.29
Summary: UNKNOWN
Home-page: UNKNOWN
Author: UNKNOWN
Author-email: UNKNOWN
License: UNKNOWN
Platform: UNKNOWN
Requires-Dist: Faker==27.0.0
Requires-Dist: mysql-connector-python==8.3.0
Requires-Dist: numpy==1.24.3
Requires-Dist: openai>=1.42.0
Requires-Dist: tqdm>=4.66.5
